geniusdotpy/__init__.py
geniusdotpy/album.py
geniusdotpy/artist.py
geniusdotpy/genius.py
geniusdotpy/track.py
geniusdotpy/utils.py
geniusdotpy-1.1.1.dist-info/LICENSE
geniusdotpy-1.1.1.dist-info/METADATA
geniusdotpy-1.1.1.dist-info/WHEEL
geniusdotpy-1.1.1.dist-info/top_level.txt
geniusdotpy-1.1.1.dist-info/RECORD
