Metadata-Version: 2.1
Name: geniusdotpy
Version: 1.1.1
Summary: Python wrapper for Genius API
Home-page: https://github.com/jjoeldaniel/genius.py
Author: jjoeldaniel
Author-email: <joeldanielrico@gmail.com>
Keywords: python,genius,api-wrapper
Classifier: Development Status :: 5 - Production/Stable
Classifier: Intended Audience :: Developers
Classifier: Programming Language :: Python :: 3
Classifier: Operating System :: Unix
Classifier: Operating System :: MacOS :: MacOS X
Classifier: Operating System :: Microsoft :: Windows
License-File: LICENSE
Requires-Dist: requests
Requires-Dist: beautifulsoup4
